{"cameraMode":{"drawMode":0,"name":"Shaded","section":"Shading Mode"},"sceneLighting":true,"audioPlay":false,"sceneViewState":{"m_AlwaysRefresh":false,"showFog":true,"showSkybox":true,"showFlares":true,"showImageEffects":true,"showParticleSystems":true,"showVisualEffectGraphs":true,"m_FxEnabled":true},"in2DMode":false,"pivot":{"x":443.32763671875,"y":408.33294677734377,"z":4.91949462890625},"rotation":{"x":-0.1289367824792862,"y":0.013979090377688408,"z":-0.0018177509773522616,"w":-0.9915531277656555},"size":103.49275970458985,"orthographic":false}